poetry_plugin_shell/__init__.py
poetry_plugin_shell/command.py
poetry_plugin_shell/plugins.py
poetry_plugin_shell/shell.py
poetry_plugin_shell-1.0.0.dist-info/LICENSE
poetry_plugin_shell-1.0.0.dist-info/METADATA
poetry_plugin_shell-1.0.0.dist-info/WHEEL
poetry_plugin_shell-1.0.0.dist-info/entry_points.txt
poetry_plugin_shell-1.0.0.dist-info/RECORD
