Metadata-Version: 2.1
Name: poetry-plugin-shell
Version: 1.0.0
Summary: Poetry plugin to run subshell with virtual environment activated
Home-page: https://python-poetry.org/
License: MIT
Author: Sébastien Eustace
Author-email: sebastien@eustace.io
Requires-Python: >=3.9,<4.0
Classifier: License :: OSI Approved :: MIT License
Classifier: Programming Language :: Python :: 3
Classifier: Programming Language :: Python :: 3.9
Classifier: Programming Language :: Python :: 3.10
Classifier: Programming Language :: Python :: 3.11
Classifier: Programming Language :: Python :: 3.12
Classifier: Programming Language :: Python :: 3.13
Requires-Dist: pexpect (>=4.7.0,<5.0.0)
Requires-Dist: poetry (>=1.8.0,<3.0.0)
Requires-Dist: shellingham (>=1.5,<2.0)
Project-URL: Repository, https://github.com/python-poetry/poetry-plugin-shell
